abilian_devtools/__init__.py
abilian_devtools/cli.py
abilian_devtools/shell.py
abilian_devtools/commands/__init__.py
abilian_devtools/commands/_util.py
abilian_devtools/commands/all.py
abilian_devtools/commands/audit.py
abilian_devtools/commands/bump.py
abilian_devtools/commands/check.py
abilian_devtools/commands/clean.py
abilian_devtools/commands/cruft.py
abilian_devtools/commands/format.py
abilian_devtools/commands/help.py
abilian_devtools/commands/seed.py
abilian_devtools/commands/test.py
abilian_devtools/commands/typecheck.py
abilian_devtools/etc/.gitignore
abilian_devtools/etc/.pre-commit-config.yaml
abilian_devtools/etc/Makefile
abilian_devtools/etc/__init__.py
abilian_devtools/etc/envrc
abilian_devtools/etc/ruff.toml
abilian_devtools/invoke/__init__.py
abilian_devtools/invoke/help.py
abilian_devtools/invoke/subrepos.py
abilian_devtools/invoke/versions.py
abilian_devtools/seed/__init__.py
abilian_devtools/seed/config.py
abilian_devtools/seed/profile.py
abilian_devtools/seed/template.py
abilian_devtools/seed/variables.py
abilian_devtools-0.9.0.dist-info/METADATA
abilian_devtools-0.9.0.dist-info/WHEEL
abilian_devtools-0.9.0.dist-info/entry_points.txt
abilian_devtools-0.9.0.dist-info/RECORD
