Metadata-Version: 2.4
Name: abilian-devtools
Version: 0.9.0
Summary: A curated set of dependencies for quality software development
Project-URL: Repository, https://github.com/abilian/abilian-devtools
Author-email: Stefane Fermigier <sf@abilian.com>
License-Expression: MIT
Keywords: linting,qa,security,supply_chain,testing
Requires-Python: <4.0,>=3.10
Requires-Dist: cleez>=0.1.11
Requires-Dist: deptry>=0.20
Requires-Dist: docformatter>=1.7.5
Requires-Dist: invoke>=2.2.0
Requires-Dist: jinja2>=3.0
Requires-Dist: nox>=2023
Requires-Dist: pre-commit>=4
Requires-Dist: profilehooks>=1
Requires-Dist: pytest-cov>=5
Requires-Dist: pytest-random-order>=1
Requires-Dist: pytest-xdist>=3
Requires-Dist: pytest>=8
Requires-Dist: reuse>=4
Requires-Dist: ruff>=0.5.1
Requires-Dist: tomlkit>=0.12
Requires-Dist: ty
Requires-Dist: vulture>=2.11
